{
	"id": 1241592,
	"title": "Khel Khel Mein",
	"fcg_title": "Khel Khel Mein",
	"original_title": "खेल खेल में",
	"original_language": "hi",
	"genres": [
		{
			"id": 35,
			"name": "Comedy"
		},
		{
			"id": 18,
			"name": "Drama"
		}
	],
	"overview": "What if for one night your mobile phone was a public property? 7 friends at a wedding after-party decide to play a seemingly harmless but as it turns out, a dangerous game which might have earth-shattering consequences with relationships, marriages and identities being at stake.",
	"backdrop_path": "/xtdfF8BICp0CZSvA3lnqqYx7eSq.jpg",
	"poster_path": "/32P0oQf41HXbENRGtu2h0rqBF2k.jpg",
	"release_date": "2024-08-15",
	"credits": {
		"cast": [
			{
				"id": 35070,
				"order": 0,
				"name": "Akshay Kumar",
				"profile_path": "/1d77rFiN8h2JXE6vS8VCuc2k20J.jpg",
				"character": "Rishabh Malik",
				"gender": 2
			},
			{
				"id": 550167,
				"order": 1,
				"name": "Taapsee Pannu",
				"profile_path": "/micyQ84KdF7rVu05SYkMxk8VGq4.jpg",
				"character": "Harpreet Kaur",
				"gender": 1
			},
			{
				"id": 1192903,
				"order": 2,
				"name": "Vaani Kapoor",
				"profile_path": "/u39OAXWXiOCQhbtLTIRBMjdaZwT.jpg",
				"character": "Vartika Malik",
				"gender": 1
			},
			{
				"id": 35069,
				"order": 3,
				"name": "Fardeen Khan",
				"profile_path": "/pr3VEjdUTOKSNBFHgwjH9rOT5nC.jpg",
				"character": "Kabir",
				"gender": 2
			},
			{
				"id": 1810686,
				"order": 4,
				"name": "Ammy Virk",
				"profile_path": "/8ZXB6vBqhV3aA0kf6OP4zrmeFsw.jpg",
				"character": "Harpreet Singh Sodhi",
				"gender": 2
			},
			{
				"id": 584595,
				"order": 5,
				"name": "Pragya Jaiswal",
				"profile_path": "/dtqZhYFniXaCvRuuFJkchH92fQZ.jpg",
				"character": "Nayna Mehra",
				"gender": 1
			},
			{
				"id": 1065023,
				"order": 6,
				"name": "Aditya Seal",
				"profile_path": "/ld6GIz09Ztd8YIyboZMeitPUVJz.jpg",
				"character": "Samar Tanwar",
				"gender": 2
			},
			{
				"id": 232828,
				"order": 7,
				"name": "Kiran Kumar",
				"profile_path": "/vnpgMjRmNXl9r6LE2N5RJ1F5gD6.jpg",
				"character": "Vartika's Father",
				"gender": 2
			},
			{
				"id": 1824436,
				"order": 8,
				"name": "Alka Kaushal",
				"character": "Vartika's Mother"
			},
			{
				"id": 2256864,
				"order": 9,
				"name": "Talat Aziz",
				"character": "Gagan Mehra (Naina's Father)"
			},
			{
				"id": 4960031,
				"order": 10,
				"name": "Diljot Chhabra",
				"character": "Radhika"
			},
			{
				"id": 4441517,
				"order": 11,
				"name": "Gaurav Manwani",
				"character": "Varun"
			},
			{
				"id": 2783187,
				"order": 12,
				"name": "Ishita Arun",
				"profile_path": "/kTXmlmaE4D378Pm5kaisbngFdYl.jpg",
				"character": "Malti",
				"gender": 1
			},
			{
				"id": 4528644,
				"order": 13,
				"name": "Maahi Raj Jain",
				"character": "Anaya"
			},
			{
				"id": 110850,
				"order": 14,
				"name": "Chitrangda Singh",
				"profile_path": "/lEKCbEO2Y9wkzSx9xO2C3foH21x.jpg",
				"character": "Kadambari Kapoor",
				"gender": 1
			},
			{
				"id": 35792,
				"order": 15,
				"name": "Jimmy Shergill",
				"profile_path": "/1Pj38LAhEceystAgXOw4oP8Sr0m.jpg",
				"character": "Voice",
				"gender": 2
			},
			{
				"id": 1434137,
				"order": 16,
				"name": "Bhumi Pednekar",
				"profile_path": "/qaMDhXyAWBV3FXEGPavXoYwh3kb.jpg",
				"character": "Sandhya (Voice)",
				"gender": 1
			},
			{
				"id": 1034470,
				"order": 17,
				"name": "Arjun Kapoor",
				"profile_path": "/24NE9QaKp66sM6C3eCsGUuleXXf.jpg",
				"character": "Voice",
				"gender": 2
			},
			{
				"id": 1756890,
				"order": 18,
				"name": "Aparshakti Khurana",
				"profile_path": "/w7OEkPAaweO1JU105Qqvg073yW8.jpg",
				"character": "Voice",
				"gender": 2
			},
			{
				"id": 1973077,
				"order": 19,
				"name": "Ananya Panday",
				"profile_path": "/wiFjU6HYsVkrJG7ExajpEbM2OZ4.jpg",
				"character": "Voice",
				"gender": 1
			},
			{
				"id": 1521297,
				"order": 20,
				"name": "Sunny Singh",
				"profile_path": "/4twDvnGB7lGUevvYDyAuBmOleCl.jpg",
				"character": "Voice",
				"gender": 2
			}
		],
		"crew": [
			{
				"id": 105166,
				"name": "Mudassar Aziz",
				"job": "Director",
				"department": "Directing"
			},
			{
				"id": 83595,
				"name": "Bhushan Kumar",
				"profile_path": "/luUFnGoGwjwZ5CHAePRIQpAwT5b.jpg",
				"job": "Producer",
				"department": "Production",
				"gender": 2
			},
			{
				"id": 3281260,
				"name": "Rajesh Bahl",
				"job": "Producer",
				"department": "Production"
			},
			{
				"id": 2204524,
				"name": "Shashikant Sinha",
				"job": "Producer",
				"department": "Production"
			},
			{
				"id": 141882,
				"name": "Krishan Kumar",
				"profile_path": "/gw2jzzkdRyIHglwieCiFSQ9cLZZ.jpg",
				"job": "Producer",
				"department": "Production",
				"gender": 2
			},
			{
				"id": 2224681,
				"name": "Ashwin Varde",
				"job": "Producer",
				"department": "Production"
			},
			{
				"id": 233070,
				"name": "Ajay Rai",
				"job": "Producer",
				"department": "Production",
				"gender": 2
			},
			{
				"id": 1279763,
				"name": "Manoj Kumar Khatoi",
				"job": "Director of Photography",
				"department": "Camera"
			},
			{
				"id": 2118233,
				"name": "Ninad Khanolkar",
				"job": "Editor",
				"department": "Editing"
			},
			{
				"id": 1797339,
				"name": "Rupin Suchak",
				"job": "Production Design",
				"department": "Art"
			},
			{
				"id": 1756135,
				"name": "Arun Nambiar",
				"job": "Sound Designer",
				"department": "Sound"
			},
			{
				"id": 2278070,
				"name": "Sanam Ratansi",
				"job": "Costume Designer",
				"department": "Costume \u0026 Make-Up"
			},
			{
				"id": 1796213,
				"name": "Vipul D. Shah",
				"job": "Producer",
				"department": "Production"
			},
			{
				"id": 2955385,
				"name": "Jassi Sidhu",
				"job": "Music",
				"department": "Sound"
			},
			{
				"id": 2955385,
				"name": "Jassi Sidhu",
				"job": "Lyricist",
				"department": "Writing"
			},
			{
				"id": 1775462,
				"name": "Tanishk Bagchi",
				"profile_path": "/lTNruwralNeUIDHBx3SC22yQOqv.jpg",
				"job": "Music",
				"department": "Sound",
				"gender": 2
			},
			{
				"id": 2441800,
				"name": "Sara Bodinar",
				"job": "Writer",
				"department": "Writing"
			},
			{
				"id": 233065,
				"name": "Kumaar",
				"profile_path": "/9sHLGuvqvmfbeh9RiaYROVQ2VUy.jpg",
				"job": "Lyricist",
				"department": "Writing",
				"gender": 2
			},
			{
				"id": 1823131,
				"name": "Guru Randhawa",
				"job": "Music",
				"department": "Sound",
				"gender": 2
			},
			{
				"id": 105166,
				"name": "Mudassar Aziz",
				"job": "Writer",
				"department": "Writing"
			},
			{
				"id": 1912301,
				"name": "Firuzi Khan",
				"job": "Producer",
				"department": "Production"
			},
			{
				"id": 2519169,
				"name": "Shiv Chanana",
				"job": "Co-Producer",
				"department": "Production"
			},
			{
				"id": 1174417,
				"name": "Rochak Kohli",
				"profile_path": "/bJ77Ut5e1dwVsTXjEYFgtJFR8A6.jpg",
				"job": "Music",
				"department": "Sound",
				"gender": 2
			}
		]
	}
}