{
	"id": 645757,
	"title": "That Christmas",
	"fcg_title": "That Christmas",
	"original_title": "That Christmas",
	"original_language": "en",
	"genres": [
		{
			"id": 16,
			"name": "Animation"
		},
		{
			"id": 35,
			"name": "Comedy"
		},
		{
			"id": 10751,
			"name": "Family"
		},
		{
			"id": 14,
			"name": "Fantasy"
		},
		{
			"id": 12,
			"name": "Adventure"
		}
	],
	"overview": "It's an unforgettable Christmas for the townsfolk of Wellington-on-Sea when the worst snowstorm in history alters everyone's plans — including Santa's.",
	"backdrop_path": "/rWs3Q9bT7zCH6t004z67UGuWUwu.jpg",
	"poster_path": "/sx86KHWwWbW5ZckPEQh39J0Fio3.jpg",
	"release_date": "2024-11-27",
	"credits": {
		"cast": [
			{
				"id": 1248,
				"order": 0,
				"name": "Brian Cox",
				"profile_path": "/yvoAgJTOvuNSPSKegcIcD62ySY9.jpg",
				"character": "Santa (voice)",
				"gender": 2
			},
			{
				"id": 2440,
				"order": 1,
				"name": "Bill Nighy",
				"profile_path": "/acbigDOU1L1vMWAL3Wf0r8h8qLA.jpg",
				"character": "Lighthouse Bill (voice)",
				"gender": 2
			},
			{
				"id": 10981,
				"order": 2,
				"name": "Fiona Shaw",
				"profile_path": "/imZ9Ad2RIPmxHZjeflF9po4WVfO.jpg",
				"character": "Ms. Trapper (voice)",
				"gender": 1
			},
			{
				"id": 4604179,
				"order": 3,
				"name": "Jack Wisniewski",
				"character": "Danny Williams (voice)"
			},
			{
				"id": 66431,
				"order": 4,
				"name": "Jodie Whittaker",
				"profile_path": "/zS6EO1GsfOiuyaa66YqmUPWDX78.jpg",
				"character": "Mrs. Williams (voice)",
				"gender": 1
			},
			{
				"id": 1672505,
				"order": 5,
				"name": "India Brown",
				"profile_path": "/hqOxRR0DBJ8Z2IKFYThCV7xcsqv.jpg",
				"character": "Bernadette McNutt (voice)",
				"gender": 1
			},
			{
				"id": 2037501,
				"order": 6,
				"name": "Guz Khan",
				"profile_path": "/pY2ND9eZhUtPuRBZPEoM1BRPZBd.jpg",
				"character": "Dasher (voice)",
				"gender": 2
			},
			{
				"id": 1627501,
				"order": 7,
				"name": "Lolly Adefope",
				"profile_path": "/qPS57Mw1vjydSSfSYoMw8u81waI.jpg",
				"character": "Mrs. McNutt (voice)",
				"gender": 1
			},
			{
				"id": 2663179,
				"order": 8,
				"name": "Zazie Hayhurst",
				"character": "Sam Beccles (voice)",
				"gender": 1
			},
			{
				"id": 2559230,
				"order": 9,
				"name": "Sienna Sayer",
				"profile_path": "/wCWSIDF5gLKfiUkAVV9uaEER3SN.jpg",
				"character": "Charlie Beccles (voice)",
				"gender": 1
			},
			{
				"id": 126042,
				"order": 10,
				"name": "Alex Macqueen",
				"profile_path": "/d8hfBJcYNXf3GJPFzKpOfkwLUg0.jpg",
				"character": "Mr. Forrest (voice)",
				"gender": 2
			},
			{
				"id": 74158,
				"order": 11,
				"name": "Katherine Parkinson",
				"profile_path": "/8broF5f3gZsySdtdbpbyiVtCn6n.jpg",
				"character": "Mrs. Forrest (voice)",
				"gender": 1
			},
			{
				"id": 1785478,
				"order": 12,
				"name": "Sindhu Vee",
				"profile_path": "/xDSGdKJ7UMZhcpau7TJgc0UpGDA.jpg",
				"character": "Mrs. Mulji (voice)",
				"gender": 1
			},
			{
				"id": 151949,
				"order": 13,
				"name": "Rosie Cavaliero",
				"profile_path": "/q9EOEphyrCGhUyDgAhFf00xAlWB.jpg",
				"character": "Mrs. Beccles (voice)",
				"gender": 1
			},
			{
				"id": 71281,
				"order": 14,
				"name": "Paul Kaye",
				"profile_path": "/bGZxKojbRrgyI3gFtRsduJnbcrm.jpg",
				"character": "Yirrell (voice)",
				"gender": 2
			},
			{
				"id": 22810,
				"order": 15,
				"name": "Andy Nyman",
				"profile_path": "/9bN9RVoPWmsmV3VBI7hp4VKD9Kg.jpg",
				"character": "Mr. Beccles (voice)",
				"gender": 2
			},
			{
				"id": 4604180,
				"order": 16,
				"name": "Kuhu Agarwal",
				"character": "Nisha Mulji (voice)"
			},
			{
				"id": 4246789,
				"order": 17,
				"name": "Bronte Smith",
				"character": "Eve McNutt (voice)"
			},
			{
				"id": 3262412,
				"order": 18,
				"name": "Freddie Spry",
				"profile_path": "/gJeg6upb4EvH8ADyfACbcz6VSzn.jpg",
				"character": "Teddy Forrest (voice)",
				"gender": 2
			},
			{
				"id": 4604187,
				"order": 19,
				"name": "Ava Talbot",
				"character": "Scarlett Forrest (voice)"
			},
			{
				"id": 82666,
				"order": 20,
				"name": "Rhys Darby",
				"profile_path": "/9lvTJroJAaAopBQlslx2LOBYJv.jpg",
				"character": "Mr. McNutt (voice)",
				"gender": 2
			},
			{
				"id": 135420,
				"order": 21,
				"name": "Deborah Findlay",
				"profile_path": "/4FbdygLj08dfo63hNCZNc36FEr1.jpg",
				"character": "Mrs. Horton (voice)",
				"gender": 1
			},
			{
				"id": 5100273,
				"order": 22,
				"name": "Alicia Davies",
				"character": "Weather Person (voice)"
			},
			{
				"id": 5065816,
				"order": 23,
				"name": "Isabella Hopkins",
				"character": "Additional Voices (voice)"
			},
			{
				"id": 1447381,
				"order": 24,
				"name": "Simon Otto",
				"profile_path": "/fwa4xcFic7w42r3sUQb9LGIN6x9.jpg",
				"character": "Additional Voices (voice)",
				"gender": 2
			},
			{
				"id": 2859650,
				"order": 25,
				"name": "Jordan North",
				"profile_path": "/6x8BVP6ENNNzsuyJ4njBwphsT1Z.jpg",
				"character": "Additional Voices (voice)",
				"gender": 2
			},
			{
				"id": 1216116,
				"order": 26,
				"name": "Dermot O'Leary",
				"profile_path": "/nNORyd0Ue51inB98MbTEMQFIQ55.jpg",
				"character": "Additional Voices (voice)",
				"gender": 2
			},
			{
				"id": 5065817,
				"order": 27,
				"name": "Luke Jameson",
				"character": "Additional Voices (voice)"
			},
			{
				"id": 5065818,
				"order": 28,
				"name": "Mary Moss",
				"character": "Additional Voices (voice)"
			}
		],
		"crew": [
			{
				"id": 1447381,
				"name": "Simon Otto",
				"profile_path": "/fwa4xcFic7w42r3sUQb9LGIN6x9.jpg",
				"job": "Director",
				"department": "Directing",
				"gender": 2
			},
			{
				"id": 1725461,
				"name": "Doug Ikeler",
				"job": "Visual Effects Supervisor",
				"department": "Visual Effects"
			},
			{
				"id": 4375779,
				"name": "Nicholas New",
				"job": "Digital Effects Supervisor",
				"department": "Crew"
			},
			{
				"id": 4375780,
				"name": "Matt Waters",
				"job": "Digital Effects Supervisor",
				"department": "Crew"
			},
			{
				"id": 4375781,
				"name": "Kapil Sharma",
				"job": "Animation Director",
				"department": "Visual Effects"
			},
			{
				"id": 1742294,
				"name": "Nicole P. Hearon",
				"job": "Producer",
				"department": "Production",
				"gender": 1
			},
			{
				"id": 1222074,
				"name": "Adam Tandy",
				"profile_path": "/eoERUf7Loak5wCPMztxriFtxCIf.jpg",
				"job": "Producer",
				"department": "Production",
				"gender": 2
			},
			{
				"id": 11098,
				"name": "John Powell",
				"profile_path": "/trywZMdhKM04PL1lH5OECXRxL1u.jpg",
				"job": "Original Music Composer",
				"department": "Sound",
				"gender": 2
			},
			{
				"id": 998387,
				"name": "Ed Sheeran",
				"profile_path": "/w7zbWC9AV0WfIEl8L38otal7mwS.jpg",
				"job": "Songs",
				"department": "Sound",
				"gender": 2
			},
			{
				"id": 7018,
				"name": "Richard Curtis",
				"profile_path": "/dLhFfcHJvOLzzykO3LYkinXJUA1.jpg",
				"job": "Book",
				"department": "Writing",
				"gender": 2
			},
			{
				"id": 7018,
				"name": "Richard Curtis",
				"profile_path": "/dLhFfcHJvOLzzykO3LYkinXJUA1.jpg",
				"job": "Screenplay",
				"department": "Writing",
				"gender": 2
			},
			{
				"id": 2450750,
				"name": "Peter Souter",
				"job": "Screenplay",
				"department": "Writing"
			},
			{
				"id": 1776809,
				"name": "Colin Hopkins",
				"job": "Executive Producer",
				"department": "Production"
			},
			{
				"id": 2450750,
				"name": "Peter Souter",
				"job": "Executive Producer",
				"department": "Production"
			},
			{
				"id": 1395024,
				"name": "Mike Prestwood Smith",
				"profile_path": "/zby8zfg7BmwJagimhCedsHepeAR.jpg",
				"job": "Sound Re-Recording Mixer",
				"department": "Sound",
				"gender": 2
			},
			{
				"id": 1338971,
				"name": "Glen Gathard",
				"job": "Supervising Sound Editor",
				"department": "Sound",
				"gender": 2
			},
			{
				"id": 63600,
				"name": "Rachel Freck",
				"job": "Casting",
				"department": "Production",
				"gender": 1
			},
			{
				"id": 5542,
				"name": "Sim Evan-Jones",
				"job": "Editor",
				"department": "Editing",
				"gender": 2
			},
			{
				"id": 1575349,
				"name": "Justin Hutchinson-Chatburn",
				"job": "Production Design",
				"department": "Art",
				"gender": 2
			},
			{
				"id": 1388195,
				"name": "Mike Redman",
				"job": "Art Direction",
				"department": "Art"
			},
			{
				"id": 12894,
				"name": "Bonnie Arnold",
				"profile_path": "/fFU68wkvil1w8gOjwCzzHysKJP0.jpg",
				"job": "Executive Producer",
				"department": "Production",
				"gender": 1
			},
			{
				"id": 60929,
				"name": "Lara Breay",
				"job": "Executive Producer",
				"department": "Production",
				"gender": 1
			},
			{
				"id": 2450751,
				"name": "Rebecca Cobb",
				"job": "Executive Producer",
				"department": "Production"
			},
			{
				"id": 2008772,
				"name": "Mary Coleman",
				"job": "Executive Producer",
				"department": "Production"
			},
			{
				"id": 7018,
				"name": "Richard Curtis",
				"profile_path": "/dLhFfcHJvOLzzykO3LYkinXJUA1.jpg",
				"job": "Executive Producer",
				"department": "Production",
				"gender": 2
			},
			{
				"id": 3425227,
				"name": "François Deschamps",
				"job": "Executive Producer",
				"department": "Production"
			},
			{
				"id": 3169415,
				"name": "Natalie Fischer",
				"job": "Executive Producer",
				"department": "Production"
			},
			{
				"id": 1537895,
				"name": "Julie Lockhart",
				"job": "Executive Producer",
				"department": "Production"
			},
			{
				"id": 1232124,
				"name": "Elisabeth Murdoch",
				"job": "Executive Producer",
				"department": "Production"
			},
			{
				"id": 2005369,
				"name": "Olivia Lyne",
				"job": "Associate Producer",
				"department": "Production"
			},
			{
				"id": 592853,
				"name": "Uwe Heidschötter",
				"job": "Lead Character Designer",
				"department": "Visual Effects",
				"gender": 2
			},
			{
				"id": 1726869,
				"name": "Leo Sanchez Barbosa",
				"job": "Character Designer",
				"department": "Visual Effects",
				"gender": 2
			},
			{
				"id": 1454664,
				"name": "Ashley Boddy",
				"job": "Head of Story",
				"department": "Writing"
			},
			{
				"id": 1453986,
				"name": "D. Edwardz",
				"profile_path": "/51kLiHJkDIKNfOYuEdGjvwB8cX.jpg",
				"job": "Head of Layout",
				"department": "Camera"
			},
			{
				"id": 223202,
				"name": "Nick Angel",
				"job": "Music Supervisor",
				"department": "Sound",
				"gender": 2
			},
			{
				"id": 1847420,
				"name": "Tom Jacomb",
				"job": "In Memory Of",
				"department": "Crew",
				"gender": 2
			},
			{
				"id": 1516079,
				"name": "Aaron Dem",
				"job": "Co-Producer",
				"department": "Production",
				"gender": 2
			},
			{
				"id": 208113,
				"name": "Sarah Smith",
				"profile_path": "/olom5l3enkaKX5qYcOoJDDF7Epq.jpg",
				"job": "Executive Producer",
				"department": "Production",
				"gender": 1
			}
		]
	}
}